MANIFEST.in
NEWS.rst
README.rst
setup.cfg
setup.py
build_scripts/__init__.py
build_scripts/version.py
src/attowiki/RELEASE-VERSION
src/attowiki/__init__.py
src/attowiki/git_tools.py
src/attowiki/main.py
src/attowiki/pdf.py
src/attowiki/rst_directives.py
src/attowiki/tools.py
src/attowiki/views.py
src/attowiki.egg-info/PKG-INFO
src/attowiki.egg-info/SOURCES.txt
src/attowiki.egg-info/dependency_links.txt
src/attowiki.egg-info/entry_points.txt
src/attowiki.egg-info/not-zip-safe
src/attowiki.egg-info/requires.txt
src/attowiki.egg-info/top_level.txt
src/attowiki/styles/pdf.style
src/attowiki/views/attowiki_docutils_css.tpl
src/attowiki/views/diff_view.tpl
src/attowiki/views/edit.tpl
src/attowiki/views/header.tpl
src/attowiki/views/header_bar.tpl
src/attowiki/views/index.tpl
src/attowiki/views/page.tpl
src/attowiki/views/rst_cheat_sheet.tpl
src/attowiki/views/source_view.tpl