Metadata-Version: 1.1
Name: attowiki
Version: v0.5
Summary: small wiki engine based on static reST files in a directory and git for versionning
Home-page: https://github.com/ThomasChiroux/attowiki
Author: Thomas Chiroux
Author-email: UNKNOWN
License: GPLv3
Keywords: restructuredText wiki
Platform: UNKNOWN
Classifier: Programming Language :: Python
Classifier: Programming Language :: Python :: 2.6
Classifier: Programming Language :: Python :: 2.7
Provides: attowiki
